pysqldbm/__init__.py
pysqldbm/client.py
pysqldbm/rest_client.py
pysqldbm_cli/__init__.py
pysqldbm_cli/run.py
pysqldbm-1.0.6.dist-info/METADATA
pysqldbm-1.0.6.dist-info/WHEEL
pysqldbm-1.0.6.dist-info/entry_points.txt
pysqldbm-1.0.6.dist-info/top_level.txt
pysqldbm-1.0.6.dist-info/RECORD
