Metadata-Version: 2.1
Name: pysqldbm
Version: 1.0.6
Summary: A library to wrap SQLdbm API
Home-page: https://github.com/drewsonne/pysqldbm
Author: Drew J. Sonne
Author-email: drew.sonne@gmail.com
License: Apache
Classifier: Programming Language :: Python :: 3
Classifier: Programming Language :: Python :: 3.10
Requires-Python: >=3.10
Requires-Dist: requests
Requires-Dist: backoff
Provides-Extra: cli
Requires-Dist: click ; extra == 'cli'
